mrktmix/__init__.py
mrktmix/__main__.py
mrktmix/cli.py
mrktmix/data_create.py
mrktmix/optimization.py
mrktmix/transformation.py
mrktmix/dataprep/__init__.py
mrktmix/dataprep/mdl_data.py
mrktmix/dataprep/transform.py
mrktmix-0.6.1.dist-info/AUTHORS.rst
mrktmix-0.6.1.dist-info/LICENSE
mrktmix-0.6.1.dist-info/METADATA
mrktmix-0.6.1.dist-info/WHEEL
mrktmix-0.6.1.dist-info/entry_points.txt
mrktmix-0.6.1.dist-info/top_level.txt
mrktmix-0.6.1.dist-info/RECORD
