Metadata-Version: 2.1
Name: mrktmix
Version: 0.6.1
Summary: Market Mix Modeling
Home-page: https://github.com/540pd/mrktmix
Author: Abhimanyu Prasad Mahato
Author-email: abhimanyu.mahato@gmail.com
License: LGPL-3.0-or-later
Project-URL: Documentation, https://market_mix_model.readthedocs.io/
Project-URL: Changelog, https://market_mix_model.readthedocs.io/en/latest/changelog.html
Project-URL: Issue Tracker, https://github.com/540pd/mrktmix/issues
Platform: UNKNOWN
Classifier: Development Status :: 5 - Production/Stable
Classifier: Intended Audience :: Developers
Classifier: License :: OSI Approved :: GNU Lesser General Public License v3 or later (LGPLv3+)
Classifier: Operating System :: POSIX
Classifier: Operating System :: Microsoft :: Windows
Classifier: Programming Language :: Python
Classifier: Programming Language :: Python :: 3.7
Classifier: Programming Language :: Python :: 3.8
Classifier: Programming Language :: Python :: Implementation :: CPython
Classifier: Programming Language :: Python :: Implementation :: PyPy
Classifier: Topic :: Utilities
Requires-Python: >=3.7
Requires-Dist: pandas (>=1.1.0)
Requires-Dist: scipy (>=1.4.0)
Requires-Dist: numpy (>=1.18.0)
Provides-Extra: dev
Requires-Dist: pytest (>=3.7) ; extra == 'dev'
